nx/main.py
nx/nixos.py
nx/profile.py
nx/utils.py
nx_nix-1.0.0.dist-info/entry_points.txt
nx_nix-1.0.0.dist-info/WHEEL
nx_nix-1.0.0.dist-info/METADATA
nx_nix-1.0.0.dist-info/RECORD
