Metadata-Version: 2.1
Name: nx-nix
Version: 1.0.0
Summary: A fast and beautiful NixOS and Nix management utility
Author: Michal
Author-email: mchal_@tuta.io
Requires-Python: >=3.10,<4.0
Classifier: Programming Language :: Python :: 3
Classifier: Programming Language :: Python :: 3.10
Requires-Dist: randomname (>=0.1.5,<0.2.0)
Requires-Dist: typer[all] (>=0.7.0,<0.8.0)
